{
  "data": [
    {
      "id": 1,
      "color": "Violet",
      "price": 106.0,
      "title": "Grapes - Red",
      "rating": 5,
      "image": "http://dummyimage.com/254x160.jpg/ff4444/ffffff"
    },
    {
      "id": 2,
      "color": "Teal",
      "price": 334.9,
      "title": "Bandage - Finger Cots",
      "rating": 2,
      "image": "http://dummyimage.com/254x160.bmp/5fa2dd/ffffff"
    },
    {
      "id": 3,
      "color": "Goldenrod",
      "price": 472.6,
      "title": "Wine - Vouvray Cuvee Domaine",
      "rating": 3,
      "image": "http://dummyimage.com/254x160.png/5fa2dd/ffffff"
    },
    {
      "id": 4,
      "color": "Blue",
      "price": 406.2,
      "title": "Cape Capensis - Fillet",
      "rating": 4,
      "image": "http://dummyimage.com/254x160.png/dddddd/000000"
    },
    {
      "id": 5,
      "color": "Yellow",
      "price": 722.0,
      "title": "Cookie Chocolate Chip With",
      "rating": 3,
      "image": "http://dummyimage.com/254x160.bmp/dddddd/000000"
    },
    {
      "id": 6,
      "color": "Orange",
      "price": 805.7,
      "title": "Dry Ice",
      "rating": 5,
      "image": "http://dummyimage.com/254x160.jpg/ff4444/ffffff"
    },
    {
      "id": 7,
      "color": "Turquoise",
      "price": 858.5,
      "title": "Oven Mitts - 15 Inch",
      "rating": 3,
      "image": "http://dummyimage.com/254x160.jpg/cc0000/ffffff"
    },
    {
      "id": 8,
      "color": "Crimson",
      "price": 266.7,
      "title": "Cookie Choc",
      "rating": 5,
      "image": "http://dummyimage.com/254x160.png/ff4444/ffffff"
    },
    {
      "id": 9,
      "color": "Teal",
      "price": 991.4,
      "title": "V8 - Berry Blend",
      "rating": 5,
      "image": "http://dummyimage.com/254x160.jpg/ff4444/ffffff"
    },
    {
      "id": 10,
      "color": "Goldenrod",
      "price": 628.8,
      "title": "Oil - Sunflower",
      "rating": 4,
      "image": "http://dummyimage.com/254x160.jpg/5fa2dd/ffffff"
    }
  ]
}
